django_mini_fastapi/__init__.py
django_mini_fastapi/api.py
django_mini_fastapi/base.py
django_mini_fastapi/enums.py
django_mini_fastapi/route.py
django_mini_fastapi/utils.py
django_mini_fastapi/fastapi/LICENSE
django_mini_fastapi/fastapi/README.md
django_mini_fastapi/fastapi/__init__.py
django_mini_fastapi/fastapi/applications.py
django_mini_fastapi/fastapi/concurrency.py
django_mini_fastapi/fastapi/datastructures.py
django_mini_fastapi/fastapi/encoders.py
django_mini_fastapi/fastapi/exception_handlers.py
django_mini_fastapi/fastapi/exceptions.py
django_mini_fastapi/fastapi/logger.py
django_mini_fastapi/fastapi/mock.py
django_mini_fastapi/fastapi/param_functions.py
django_mini_fastapi/fastapi/params.py
django_mini_fastapi/fastapi/routing.py
django_mini_fastapi/fastapi/types.py
django_mini_fastapi/fastapi/utils.py
django_mini_fastapi/fastapi/dependencies/__init__.py
django_mini_fastapi/fastapi/dependencies/models.py
django_mini_fastapi/fastapi/dependencies/utils.py
django_mini_fastapi/fastapi/openapi/__init__.py
django_mini_fastapi/fastapi/openapi/constants.py
django_mini_fastapi/fastapi/openapi/docs.py
django_mini_fastapi/fastapi/openapi/models.py
django_mini_fastapi/fastapi/openapi/utils.py
django_mini_fastapi/fastapi/security/__init__.py
django_mini_fastapi/fastapi/security/api_key.py
django_mini_fastapi/fastapi/security/base.py
django_mini_fastapi/fastapi/security/http.py
django_mini_fastapi/fastapi/security/oauth2.py
django_mini_fastapi/fastapi/security/open_id_connect_url.py
django_mini_fastapi/fastapi/security/utils.py
django_mini_fastapi-0.1.12.dist-info/LICENSE
django_mini_fastapi-0.1.12.dist-info/WHEEL
django_mini_fastapi-0.1.12.dist-info/METADATA
django_mini_fastapi-0.1.12.dist-info/RECORD
