Metadata-Version: 2.1
Name: django-mini-fastapi
Version: 0.1.12
Summary: Minimal FastAPI implementation for Django
Author-email: toki <toki.kanno@gmail.com>
Requires-Python: >=3.6
Classifier: License :: OSI Approved :: MIT License
Classifier: Programming Language :: Python :: 3 :: Only
Classifier: Programming Language :: Python :: 3.6
Classifier: Programming Language :: Python :: 3.7
Classifier: Programming Language :: Python :: 3.8
Classifier: Programming Language :: Python :: 3.9
Classifier: Framework :: Django
Classifier: Environment :: Web Environment
Classifier: Operating System :: OS Independent
Classifier: Development Status :: 2 - Pre-Alpha
Requires-Dist: django >= 1.11
Requires-Dist: pydantic >=1.6.2,!=1.7,!=1.7.1,!=1.7.2,!=1.7.3,!=1.8,!=1.8.1,<2.0.0
Project-URL: Home, https://github.com/tokikanno/django-mini-fastapi
